pandas_read_xml.py
pandas_read_xml-0.3.0.dist-info/LICENSE
pandas_read_xml-0.3.0.dist-info/METADATA
pandas_read_xml-0.3.0.dist-info/WHEEL
pandas_read_xml-0.3.0.dist-info/top_level.txt
pandas_read_xml-0.3.0.dist-info/RECORD
