Metadata-Version: 2.1
Name: pandas-read-xml
Version: 0.3.0
Summary: A tool to read XML files as pandas dataframes.
Home-page: https://github.com/minchulkim87/pandas_read_xml
Author: Min Chul Kim
Author-email: minchulkim87@gmail.com
License: UNKNOWN
Platform: UNKNOWN
Classifier: Programming Language :: Python :: 3
Classifier: License :: OSI Approved :: MIT License
Classifier: Operating System :: OS Independent
Requires-Python: >=3.6
Requires-Dist: pyarrow
Requires-Dist: pandas
Requires-Dist: xmltodict
Requires-Dist: requests
Requires-Dist: zipfile36
Requires-Dist: distlib
Requires-Dist: urllib3 (>=1.26.3)
